explorium_mcp_server/__init__.py
explorium_mcp_server/__main__.py
explorium_mcp_server/_shared.py
explorium_mcp_server/tools_businesses.py
explorium_mcp_server/tools_prospects.py
explorium_mcp_server/models/__init__.py
explorium_mcp_server/models/_shared.py
explorium_mcp_server/models/businesses.py
explorium_mcp_server/models/prospects.py
supercorp_explorium_mcp_server-0.1.3.dist-info/METADATA
supercorp_explorium_mcp_server-0.1.3.dist-info/WHEEL
supercorp_explorium_mcp_server-0.1.3.dist-info/entry_points.txt
supercorp_explorium_mcp_server-0.1.3.dist-info/licenses/LICENSE.md
supercorp_explorium_mcp_server-0.1.3.dist-info/RECORD
