Metadata-Version: 2.4
Name: supercorp-explorium-mcp-server
Version: 0.1.3
Summary: MCP server for interacting with the Explorium API.
License-File: LICENSE.md
Requires-Python: >=3.10
Requires-Dist: mcp[cli]>=1.3.0
Requires-Dist: requests>=2.32.3
